nested2dataframe/README.MD
nested2dataframe/__init__.py
nested2dataframe/requirements.txt
nested2dataframe/thirdparty.json
nested2dataframe-0.10.dist-info/LICENSE.rst
nested2dataframe-0.10.dist-info/METADATA
nested2dataframe-0.10.dist-info/WHEEL
nested2dataframe-0.10.dist-info/top_level.txt
nested2dataframe-0.10.dist-info/RECORD
