Metadata-Version: 2.1
Name: nested2dataframe
Version: 0.10
Summary: Transforms a nested dictionary or iterable into a Pandas DataFrame
Home-page: https://github.com/hansalemaos/nested2dataframe
Author: Johannes Fischer
Author-email: aulasparticularesdealemaosp@gmail.com
License: MIT
Keywords: nested,dict,DataFrame,json
Classifier: Development Status :: 4 - Beta
Classifier: Programming Language :: Python :: 3 :: Only
Classifier: Programming Language :: Python :: 3.10
Classifier: Topic :: Software Development :: Libraries :: Python Modules
Classifier: Topic :: Utilities
License-File: LICENSE.rst
Requires-Dist: a-pandas-ex-less-memory-more-speed
Requires-Dist: a-pandas-ex-plode-tool
Requires-Dist: check-if-nan
Requires-Dist: flatten-any-dict-iterable-or-whatsoever
Requires-Dist: functionapplydict
Requires-Dist: numpy
Requires-Dist: pandas
